distnet/__init__.py
distnet/data_generator/__init__.py
distnet/data_generator/dy_iterator.py
distnet/data_generator/image_data_generator_mm.py
distnet/data_generator/image_data_generator_swim.py
distnet/keras_models/__init__.py
distnet/keras_models/attention.py
distnet/keras_models/attention_self_attention.py
distnet/keras_models/intensity_transformer.py
distnet/keras_models/layers.py
distnet/keras_models/multihead_self_attention.py
distnet/keras_models/self_attention.py
distnet/keras_models/unet.py
distnet/utils/__init__.py
distnet/utils/callbacks.py
distnet/utils/helpers.py
distnet/utils/losses.py
distnet/utils/lovasz_losses_tf.py
distnet/utils/metrics.py
distnet/utils/pre_processing.py
DiST_Net-0.1.2.dist-info/LICENSE.txt
DiST_Net-0.1.2.dist-info/METADATA
DiST_Net-0.1.2.dist-info/WHEEL
DiST_Net-0.1.2.dist-info/top_level.txt
DiST_Net-0.1.2.dist-info/RECORD
