Metadata-Version: 2.1
Name: DiST-Net
Version: 0.1.2
Summary: keras implementation of DiSTNet & utilities for mother machine data analysis with keras
Home-page: https://github.com/jeanollion/distnet
Author: Jean Ollion
Author-email: jean.ollion@polytechnique.org
License: UNKNOWN
Download-URL: https://github.com/jeanollion/distnet/archive/v_01.tar.gz
Keywords: Segmentation,Tracking,SelfAttention,Tensorflow,Keras
Platform: UNKNOWN
Classifier: Development Status :: 4 - Beta
Classifier: Intended Audience :: Science/Research
Classifier: Topic :: Scientific/Engineering :: Artificial Intelligence
Classifier: Topic :: Scientific/Engineering :: Image Processing
Classifier: License :: OSI Approved :: GNU General Public License v3 or later (GPLv3+)
Classifier: Programming Language :: Python :: 3
Requires-Python: >=3
Requires-Dist: numpy
Requires-Dist: scipy
Requires-Dist: tensorflow
Requires-Dist: keras-preprocessing
Requires-Dist: edt (==2.0.2)
Requires-Dist: dataset-iterator (>=0.2.1)
